README.rst
setup.py
django_tapatalk.egg-info/PKG-INFO
django_tapatalk.egg-info/SOURCES.txt
django_tapatalk.egg-info/dependency_links.txt
django_tapatalk.egg-info/top_level.txt
tapatalk/__init__.py
tapatalk/dispatcher.py
tapatalk/forum.py
tapatalk/pm.py
tapatalk/post.py
tapatalk/search.py
tapatalk/settings.py
tapatalk/subscription.py
tapatalk/tests.py
tapatalk/topic.py
tapatalk/urls.py
tapatalk/user.py
tapatalk/util.py
tapatalk/views.py
tapatalk/tests/__init__.py
tapatalk/tests/transport.py