Metadata-Version: 1.0
Name: django-tapatalk
Version: 0.5.4
Summary: DjangoBB Tapatalk implementation
Home-page: http://github.com/svdgraaf/django-tapatalk/
Author: Sander van de Graaf
Author-email: mail@svdgraaf.nl
License: UNKNOWN
Platform: UNKNOWN
Classifier: Development Status :: 3 - Alpha
Classifier: Intended Audience :: Developers
Classifier: Framework :: Django
Classifier: License :: OSI Approved :: GNU General Public License v3 (GPLv3)
Classifier: Natural Language :: English
Classifier: Operating System :: OS Independent
Classifier: Programming Language :: Python
Classifier: Topic :: Software Development :: Libraries :: Python Modules
Classifier: Environment :: Web Environment
